tgz_message/__init__.py
tgz_message/client/__init__.py
tgz_message/client/email/__init__.py
tgz_message/client/whatsapp/__init__.py
tgz_message/delivery/__init__.py
tgz_message/delivery/broadcast/__init__.py
tgz_message/delivery/broadcast/email/__init__.py
tgz_message/delivery/broadcast/whatsapp/__init__.py
tgz_message/delivery/broadcast/whatsapp/document/__init__.py
tgz_message/delivery/broadcast/whatsapp/event/__init__.py
tgz_message/delivery/broadcast/whatsapp/template/__init__.py
tgz_message/delivery/broadcast/whatsapp/template/named/__init__.py
tgz_message/delivery/broadcast/whatsapp/template/positional/__init__.py
tgz_message/delivery/broadcast/whatsapp/text/__init__.py
tgz_message/delivery/bulk/__init__.py
tgz_message/delivery/bulk/email/__init__.py
tgz_message/delivery/bulk/whatsapp/__init__.py
tgz_message/delivery/direct/__init__.py
tgz_message/delivery/direct/email/__init__.py
tgz_message/delivery/direct/whatsapp/__init__.py
tgz_message/delivery/direct/whatsapp/document/__init__.py
tgz_message/delivery/direct/whatsapp/event/__init__.py
tgz_message/delivery/direct/whatsapp/template/__init__.py
tgz_message/delivery/direct/whatsapp/template/named/__init__.py
tgz_message/delivery/direct/whatsapp/template/positional/__init__.py
tgz_message/delivery/direct/whatsapp/text/__init__.py
tgz_message/messaging/__init__.py
tgz_message/messaging/tgz/__init__.py
tgz_message/rest/__init__.py
tgz_message/rest/domain/__init__.py
tgz_message/rest/request/__init__.py
tgz_message_sdk-0.0.7.dist-info/METADATA
tgz_message_sdk-0.0.7.dist-info/WHEEL
tgz_message_sdk-0.0.7.dist-info/top_level.txt
tgz_message_sdk-0.0.7.dist-info/RECORD
