Metadata-Version: 2.4
Name: tgz-message-sdk
Version: 0.0.7
Summary: An Official Python SDK from TechGenzi for sending messages across multiple channels like WhatsApp, Email, and SMS.
Author-email: Suwethan M <suwethan.tgz@gmail.com>
License: MIT
Requires-Python: >=3.7
Requires-Dist: requests
